CHANGELOG.md
LICENSE
README.md
kanp/__init__.py
kanp/cli.py
kanp/download.py
kanp/server.py
kanp/utils.py
pyproject.toml
kanp-0.1.0.dist-info/entry_points.txt
kanp-0.1.0.dist-info/LICENSE
kanp-0.1.0.dist-info/WHEEL
kanp-0.1.0.dist-info/METADATA
kanp-0.1.0.dist-info/RECORD
