Metadata-Version: 2.1
Name: kanp
Version: 0.1.0
Summary: See video with downloading by multithread
Home-page: https://github.com/long2ice/kanp
License: Apache-2.0
Author: long2ice
Author-email: long2ice@gmail.com
Requires-Python: >=3.7,<4.0
Classifier: License :: OSI Approved :: Apache Software License
Classifier: Programming Language :: Python :: 3
Classifier: Programming Language :: Python :: 3.7
Classifier: Programming Language :: Python :: 3.8
Requires-Dist: fastapi
Requires-Dist: httpx
Requires-Dist: uvicorn
Requires-Dist: youtube_dl
Project-URL: Documentation, https://github.com/long2ice/kanp
Project-URL: Repository, https://github.com/long2ice/kanp.git
